{
  "course_key": "mathematical_foundations_of_ai_and_ml",
  "course_title": "Mathematical Foundations of AI & ML",
  "unit_num": "02",
  "unit_title": "Linear Algebra Refresher; Covariance, PCA/SVD",
  "deck": "01_intro.html",
  "prev_url": "../01_learning_vs_data_analysis/01_intro.html",
  "prev_title": "Unit 01 \u2014 Learning vs Data Analysis; Models, Loss Functions",
  "next_url": "../03_regression_as_loss_minimization/01_intro.html",
  "next_title": "Unit 03 \u2014 Regression as Loss Minimization",
  "site_index": "../../index.html"
}
